README.md
setup.cfg
setup.py
Raney/__init__.py
Raney.egg-info/PKG-INFO
Raney.egg-info/SOURCES.txt
Raney.egg-info/dependency_links.txt
Raney.egg-info/top_level.txt