Metadata-Version: 2.1
Name: Raney
Version: 1.0.0.4
Summary: Essa biblioteca foi desenvolvida para ser mais fácil a criação de combinações rápidas.
Home-page: https://github.com/R0htg0r
Author: R0htg0r
Author-email: osvaldo.pedreiro.ecaminhoneiro@gmail.com
License: MIT
Keywords: Python3,Python2,Python,Raney,Password,Combinações,API Password
Platform: UNKNOWN
Classifier: License :: OSI Approved :: MIT License
Classifier: Programming Language :: Python :: 3.6
Classifier: Programming Language :: Python :: 3.7
Classifier: Programming Language :: Python :: 3.8
